plone.app.vocabularies-6.0.4-py3.13-nspkg.pth
plone/app/vocabularies/__init__.py
plone/app/vocabularies/actions.py
plone/app/vocabularies/catalog.py
plone/app/vocabularies/configure.zcml
plone/app/vocabularies/datetimerelated.py
plone/app/vocabularies/editors.py
plone/app/vocabularies/groups.py
plone/app/vocabularies/images.py
plone/app/vocabularies/interfaces.py
plone/app/vocabularies/language.py
plone/app/vocabularies/metadatafields.py
plone/app/vocabularies/principals.py
plone/app/vocabularies/searchabletextsource.pt
plone/app/vocabularies/security.py
plone/app/vocabularies/skins.py
plone/app/vocabularies/syndication.py
plone/app/vocabularies/terms.py
plone/app/vocabularies/testing.py
plone/app/vocabularies/types.py
plone/app/vocabularies/users.py
plone/app/vocabularies/utils.py
plone/app/vocabularies/workflow.py
plone/app/vocabularies/tests/__init__.py
plone/app/vocabularies/tests/base.py
plone/app/vocabularies/tests/test_editors.py
plone/app/vocabularies/tests/test_imagesvocabularies.py
plone/app/vocabularies/tests/test_principals.py
plone/app/vocabularies/tests/test_subjects_under_context.py
plone/app/vocabularies/tests/test_timezonevocabularies.py
plone/app/vocabularies/tests/test_vocabularies.py
plone_app_vocabularies-6.0.4.dist-info/licenses/LICENSE.GPL
plone_app_vocabularies-6.0.4.dist-info/licenses/LICENSE.txt
plone_app_vocabularies-6.0.4.dist-info/METADATA
plone_app_vocabularies-6.0.4.dist-info/WHEEL
plone_app_vocabularies-6.0.4.dist-info/namespace_packages.txt
plone_app_vocabularies-6.0.4.dist-info/top_level.txt
plone_app_vocabularies-6.0.4.dist-info/RECORD
