Metadata-Version: 2.4
Name: plone.app.vocabularies
Version: 6.0.4
Summary: Collection of generally useful vocabularies for Plone.
Home-page: https://github.com/plone/plone.app.vocabularies
Author: Plone Foundation
Author-email: plone-developers@lists.sourceforge.net
License: GPL version 2
Keywords: Plone Zope vocabularies
Classifier: Development Status :: 6 - Mature
Classifier: Environment :: Web Environment
Classifier: Framework :: Plone
Classifier: Framework :: Plone :: Core
Classifier: Framework :: Plone :: 6.0
Classifier: Framework :: Zope :: 5
Classifier: License :: OSI Approved :: GNU General Public License v2 (GPLv2)
Classifier: Operating System :: OS Independent
Classifier: Programming Language :: Python
Classifier: Programming Language :: Python :: 3.8
Classifier: Programming Language :: Python :: 3.9
Classifier: Programming Language :: Python :: 3.10
Classifier: Programming Language :: Python :: 3.11
Requires-Python: >=3.8
License-File: LICENSE.GPL
License-File: LICENSE.txt
Requires-Dist: Products.ZCatalog
Requires-Dist: plone.base
Requires-Dist: plone.memoize
Requires-Dist: plone.namedfile
Requires-Dist: plone.registry
Requires-Dist: plone.uuid
Requires-Dist: pytz
Requires-Dist: setuptools
Requires-Dist: unidecode
Requires-Dist: z3c.formwidget.query
Requires-Dist: Zope
Provides-Extra: test
Requires-Dist: plone.app.testing; extra == "test"
Requires-Dist: Products.ExtendedPathIndex; extra == "test"
Requires-Dist: zope.configuration; extra == "test"
Dynamic: author
Dynamic: author-email
Dynamic: classifier
Dynamic: description
Dynamic: description-content-type
Dynamic: home-page
Dynamic: keywords
Dynamic: license
Dynamic: license-file
Dynamic: provides-extra
Dynamic: requires-dist
Dynamic: requires-python
Dynamic: summary
